[{"blog_id":179534977,"slug":"alves","title":"Alves","site_url":"https://alvesstarter.wordpress.com","demo_url":"https://public-api.wordpress.com/rest/v1/template/demo/alves/alves/?language=en","screenshot":"https://headstartdata.files.wordpress.com/2020/01/about-4.png?w=200&zoom=1","theme":"twenty-twenty"},{"blog_id":179536505,"slug":"balasana","title":"Bālāsana","site_url":"https://balasanastarter.wordpress.com","demo_url":"https://public-api.wordpress.com/rest/v1/template/demo/balasana/balasana/?language=en","screenshot":"https://headstartdata.files.wordpress.com/2020/01/about-4.png?w=200&zoom=1","theme":"twenty-twenty"},{"blog_id":179553426,"slug":"barnsbury","title":"Barnsbury","site_url":"https://barnsburystarter.wordpress.com","demo_url":"https://public-api.wordpress.com/rest/v1/template/demo/barnsbury/barnsbury/?language=en","screenshot":"https://headstartdata.files.wordpress.com/2020/01/about-4.png?w=200&zoom=1","theme":"twenty-twenty"},{"blog_id":179593817,"slug":"bowen","title":"Bowen","site_url":"https://bowenstarterdesign.wordpress.com","demo_url":"https://public-api.wordpress.com/rest/v1/template/demo/coutoire/bowen/?language=en","screenshot":"https://headstartdata.files.wordpress.com/2020/01/about-4.png?w=200&zoom=1","theme":"twenty-twenty"},{"blog_id":179553674,"slug":"brice","title":"Brice","site_url":"https://bricestarter.wordpress.com","demo_url":"https://public-api.wordpress.com/rest/v1/template/demo/mayland/brice/?language=en","screenshot":"https://headstartdata.files.wordpress.com/2020/01/about-4.png?w=200&zoom=1","theme":"twenty-twenty"},{"blog_id":179592907,"slug":"camdem","title":"Camdem","site_url":"https://camdemstarter.wordpress.com","demo_url":"https://public-api.wordpress.com/rest/v1/template/demo/maywood/camdem/?language=en","screenshot":"https://headstartdata.files.wordpress.com/2020/01/about-4.png?w=200&zoom=1","theme":"twenty-twenty"},{"blog_id":179571208,"slug":"cassel","title":"Cassel","site_url":"https://casselstarter.wordpress.com","demo_url":"https://public-api.wordpress.com/rest/v1/template/demo/mayland/cassel/?language=en","screenshot":"https://headstartdata.files.wordpress.com/2020/01/about-4.png?w=200&zoom=1","theme":"twenty-twenty"},{"blog_id":179532527,"slug":"coutoire","title":"Coutoire","site_url":"https://coutoirestarter.wordpress.com","demo_url":"https://public-api.wordpress.com/rest/v1/template/demo/coutoire/coutoire/?language=en","screenshot":"https://headstartdata.files.wordpress.com/2020/01/about-4.png?w=200&zoom=1","theme":"twenty-twenty"},{"blog_id":179602663,"slug":"doyle","title":"Doyle","site_url":"https://doylestarter.wordpress.com","demo_url":"https://public-api.wordpress.com/rest/v1/template/demo/alves/doyle/?language=en","screenshot":"https://headstartdata.files.wordpress.com/2020/01/about-4.png?w=200&zoom=1","theme":"twenty-twenty"},{"blog_id":179588082,"slug":"easley","title":"Easley","site_url":"https://easleystarter.wordpress.com","demo_url":"https://public-api.wordpress.com/rest/v1/template/demo/maywood/easley/?language=en","screenshot":"https://headstartdata.files.wordpress.com/2020/01/about-4.png?w=200&zoom=1","theme":"twenty-twenty"},{"blog_id":179563644,"slug":"edison","title":"Edison","site_url":"https://edisonstarter.wordpress.com","demo_url":"https://public-api.wordpress.com/rest/v1/template/demo/stratford/edison/?language=en","screenshot":"https://headstartdata.files.wordpress.com/2020/01/about-4.png?w=200&zoom=1","theme":"twenty-twenty"},{"blog_id":179523106,"slug":"gibbs","title":"Gibbs","site_url":"https://gibbsstarter.wordpress.com","demo_url":"https://public-api.wordpress.com/rest/v1/template/demo/rockfield/gibbs/?language=en","screenshot":"https://headstartdata.files.wordpress.com/2020/01/about-4.png?w=200&zoom=1","theme":"twenty-twenty"},{"blog_id":181654997,"slug":"ibis","title":"Ibis","site_url":"https://ibisstarter.wordpress.com","demo_url":"https://public-api.wordpress.com/rest/v1/template/demo/ibis/ibis/?language=en","screenshot":"https://headstartdata.files.wordpress.com/2020/01/about-4.png?w=200&zoom=1","theme":"twenty-twenty"},{"blog_id":179531929,"slug":"leven","title":"Leven","site_url":"https://levenstarter.wordpress.com","demo_url":"https://public-api.wordpress.com/rest/v1/template/demo/leven/leven/?language=en","screenshot":"https://headstartdata.files.wordpress.com/2020/01/about-4.png?w=200&zoom=1","theme":"twenty-twenty"},{"blog_id":179553172,"slug":"mayland","title":"Mayland","site_url":"https://maylandstarter.wordpress.com","demo_url":"https://public-api.wordpress.com/rest/v1/template/demo/mayland/mayland/?language=en","screenshot":"https://headstartdata.files.wordpress.com/2020/01/about-4.png?w=200&zoom=1","theme":"twenty-twenty"},{"blog_id":179552586,"slug":"maywood","title":"Maywood","site_url":"https://maywoodstarter.wordpress.com","demo_url":"https://public-api.wordpress.com/rest/v1/template/demo/maywood/maywood/?language=en","screenshot":"https://headstartdata.files.wordpress.com/2020/01/about-4.png?w=200&zoom=1","theme":"twenty-twenty"},{"blog_id":179552455,"slug":"overton","title":"Overton","site_url":"https://overtonstarter.wordpress.com","demo_url":"https://public-api.wordpress.com/rest/v1/template/demo/alves/overton/?language=en","screenshot":"https://headstartdata.files.wordpress.com/2020/01/about-4.png?w=200&zoom=1","theme":"twenty-twenty"},{"blog_id":179533634,"slug":"rockfield","title":"Rockfield","site_url":"https://rockfieldstarter.wordpress.com","demo_url":"https://public-api.wordpress.com/rest/v1/template/demo/rockfield/rockfield/?language=en","screenshot":"https://headstartdata.files.wordpress.com/2020/01/about-4.png?w=200&zoom=1","theme":"twenty-twenty"},{"blog_id":179552904,"slug":"rivington","title":"Rivington","site_url":"https://rivingtonstarter.wordpress.com","demo_url":"https://public-api.wordpress.com/rest/v1/template/demo/rivington/rivington/?language=en","screenshot":"https://headstartdata.files.wordpress.com/2020/01/about-4.png?w=200&zoom=1","theme":"twenty-twenty"},{"blog_id":179533949,"slug":"stratford","title":"Stratford","site_url":"https://stratfordstarter.wordpress.com","demo_url":"https://public-api.wordpress.com/rest/v1/template/demo/stratford/stratford/?language=en","screenshot":"https://headstartdata.files.wordpress.com/2020/01/about-4.png?w=200&zoom=1","theme":"twenty-twenty"},{"blog_id":179586687,"slug":"reynolds","title":"Reynolds","site_url":"https://reynoldsstarter.wordpress.com","demo_url":"https://public-api.wordpress.com/rest/v1/template/demo/rockfield/reynolds/?language=en","screenshot":"https://headstartdata.files.wordpress.com/2020/01/about-4.png?w=200&zoom=1","theme":"twenty-twenty"},{"blog_id":181765698,"slug":"reynolds-fse","title":"Reynolds","site_url":"https://reynoldsfullsiteeditingstarter.wordpress.com","demo_url":"https://public-api.wordpress.com/rest/v1/template/demo/seedlet-blocks/reynolds-fse/?language=en","screenshot":"https://headstartdata.files.wordpress.com/2020/01/about-4.png?w=200&zoom=1","theme":"twenty-twenty"},{"blog_id":179528107,"slug":"vesta","title":"Vesta","site_url":"https://vestastarter.wordpress.com","demo_url":"https://public-api.wordpress.com/rest/v1/template/demo/mayland/vesta/?language=en","screenshot":"https://headstartdata.files.wordpress.com/2020/01/about-4.png?w=200&zoom=1","theme":"twenty-twenty"}]
